pulser/__init__.py
pulser/_version.py
pulser/abstract_repr.py
pulser/backends.py
pulser/constants.py
pulser/noise_model.py
pulser/pulse.py
pulser/py.typed
pulser/result.py
pulser/waveforms.py
pulser/_hamiltonian_data/__init__.py
pulser/_hamiltonian_data/hamiltonian_data.py
pulser/_hamiltonian_data/noise_trajectory.py
pulser/backend/__init__.py
pulser/backend/abc.py
pulser/backend/aggregators.py
pulser/backend/config.py
pulser/backend/default_observables.py
pulser/backend/observable.py
pulser/backend/operator.py
pulser/backend/qpu.py
pulser/backend/remote.py
pulser/backend/results.py
pulser/backend/state.py
pulser/channels/__init__.py
pulser/channels/base_channel.py
pulser/channels/channels.py
pulser/channels/dmm.py
pulser/channels/eom.py
pulser/devices/__init__.py
pulser/devices/_device_datacls.py
pulser/devices/_devices.py
pulser/devices/_mock_device.py
pulser/devices/interaction_coefficients/C6_coeffs.json
pulser/devices/interaction_coefficients/__init__.py
pulser/exceptions/__init__.py
pulser/exceptions/base.py
pulser/exceptions/sequence.py
pulser/exceptions/serialization.py
pulser/json/__init__.py
pulser/json/coders.py
pulser/json/exceptions.py
pulser/json/supported.py
pulser/json/utils.py
pulser/json/abstract_repr/__init__.py
pulser/json/abstract_repr/backend.py
pulser/json/abstract_repr/deserializer.py
pulser/json/abstract_repr/serializer.py
pulser/json/abstract_repr/signatures.py
pulser/json/abstract_repr/validation.py
pulser/json/abstract_repr/schemas/config-schema.json
pulser/json/abstract_repr/schemas/device-schema.json
pulser/json/abstract_repr/schemas/layout-schema.json
pulser/json/abstract_repr/schemas/noise-schema.json
pulser/json/abstract_repr/schemas/register-schema.json
pulser/json/abstract_repr/schemas/results-schema.json
pulser/json/abstract_repr/schemas/sequence-schema.json
pulser/math/__init__.py
pulser/math/abstract_array.py
pulser/math/multinomial.py
pulser/parametrized/__init__.py
pulser/parametrized/decorators.py
pulser_core-1.6.3.dist-info/licenses/LICENSE
pulser_core-1.6.3.dist-info/METADATA
pulser_core-1.6.3.dist-info/WHEEL
pulser_core-1.6.3.dist-info/top_level.txt
pulser_core-1.6.3.dist-info/RECORD
